hurt/__init__.py
hurt/middleware.py
hurt/router.py
hurt-1.0.0.dist-info/DESCRIPTION.rst
hurt-1.0.0.dist-info/METADATA
hurt-1.0.0.dist-info/RECORD
hurt-1.0.0.dist-info/WHEEL
hurt-1.0.0.dist-info/metadata.json
hurt-1.0.0.dist-info/top_level.txt
