Metadata-Version: 2.0
Name: hurt
Version: 1.0.0
Summary: Tornado middlwares
Home-page: https://github.com/hurter/hurt
Author: hurter
Author-email: ty1135@my.bristol.ac.uk
License: MIT
Keywords: tornado
Platform: UNKNOWN
Classifier: Development Status :: 3 - Alpha
Classifier: Intended Audience :: Developers
Classifier: Topic :: Software Development :: Build Tools
Classifier: License :: OSI Approved :: MIT License
Classifier: Programming Language :: Python :: 2
Classifier: Programming Language :: Python :: 2.6
Classifier: Programming Language :: Python :: 2.7
Classifier: Programming Language :: Python :: 3
Classifier: Programming Language :: Python :: 3.3
Classifier: Programming Language :: Python :: 3.4
Classifier: Programming Language :: Python :: 3.5
Requires-Dist: tornado
